CHANGES.rst
LICENSE
MANIFEST.in
MANIFEST.in.bak
README.rst
gulpfile.js
package.json
scss-lint.yml
setup.py
tox.ini
demo_docs/Makefile
demo_docs/source/__init__.py
demo_docs/source/api.rst
demo_docs/source/conf.py
demo_docs/source/demo.rst
demo_docs/source/index.rst
demo_docs/source/list.rst
demo_docs/source/long.rst
demo_docs/source/toc.rst
demo_docs/source/static/logo.png
demo_docs/source/static/redactor-logo-old.png
demo_docs/source/static/redactor-logo.png
demo_docs/source/static/yi_jing_01_chien.jpg
demo_docs/source/test_py_module/__init__.py
demo_docs/source/test_py_module/test.py
docs/_static/redactor_theme.png
js/theme.js
sass/_buttons.scss
sass/_components.scss
sass/_elements.scss
sass/_reset.scss
sass/_settings.scss
sass/_smartphone.scss
sass/_utils.scss
sass/jast.scss
sass/mdi/_core.scss
sass/mdi/_extras.scss
sass/mdi/_icons.scss
sass/mdi/_materialdesignicons.scss
sass/mdi/_path.scss
sass/mdi/_variables.scss
sphinx_redactor_theme/__init__.py
sphinx_redactor_theme/breadcrumbs.html
sphinx_redactor_theme/footer.html
sphinx_redactor_theme/layout.html
sphinx_redactor_theme/search.html
sphinx_redactor_theme/searchbox.html
sphinx_redactor_theme/sidebar.html
sphinx_redactor_theme/theme.conf
sphinx_redactor_theme/versions.html
sphinx_redactor_theme.egg-info/PKG-INFO
sphinx_redactor_theme.egg-info/SOURCES.txt
sphinx_redactor_theme.egg-info/dependency_links.txt
sphinx_redactor_theme.egg-info/not-zip-safe
sphinx_redactor_theme.egg-info/top_level.txt
sphinx_redactor_theme/static/css/jast.css
sphinx_redactor_theme/static/css/redactor.css
sphinx_redactor_theme/static/fonts/materialdesignicons-webfont.eot
sphinx_redactor_theme/static/fonts/materialdesignicons-webfont.svg
sphinx_redactor_theme/static/fonts/materialdesignicons-webfont.ttf
sphinx_redactor_theme/static/fonts/materialdesignicons-webfont.woff
sphinx_redactor_theme/static/fonts/materialdesignicons-webfont.woff2
sphinx_redactor_theme/static/js/theme-min.js