Metadata-Version: 1.1
Name: sphinx-redactor-theme
Version: 0.0.1
Summary: Sphinx theme for redactor docs.
Home-page: https://github.com/testthedocs/sphinx_redactor_theme
Author: TestTheDocs Community
Author-email: info@testthedocs.org
License: MIT
Platform: UNKNOWN
Classifier: Development Status :: 3 - Alpha
Classifier: License :: OSI Approved :: BSD License
Classifier: Environment :: Console
Classifier: Environment :: Web Environment
Classifier: Intended Audience :: Developers
Classifier: Programming Language :: Python :: 2.7
Classifier: Programming Language :: Python :: 3
Classifier: Operating System :: OS Independent
Classifier: Topic :: Documentation
Classifier: Topic :: Software Development :: Documentation
